promptz/__init__.py
promptz/cli.py
promptz-0.0.10.dist-info/LICENSE
promptz-0.0.10.dist-info/METADATA
promptz-0.0.10.dist-info/WHEEL
promptz-0.0.10.dist-info/entry_points.txt
promptz-0.0.10.dist-info/top_level.txt
promptz-0.0.10.dist-info/RECORD
