Metadata-Version: 2.1
Name: promptz
Version: 0.0.10
Summary: A Python package for interactive prompts
Home-page: UNKNOWN
License: UNKNOWN
Platform: UNKNOWN
License-File: LICENSE
Requires-Dist: Jinja2 (==3.1.2)
Requires-Dist: MarkupSafe (==2.1.3)
Requires-Dist: PyPika (==0.48.9)
Requires-Dist: PyYAML (==6.0.1)
Requires-Dist: Pygments (==2.15.1)
Requires-Dist: aiohttp (==3.8.5)
Requires-Dist: aiosignal (==1.3.1)
Requires-Dist: anyio (==3.7.1)
Requires-Dist: asttokens (==2.2.1)
Requires-Dist: async-timeout (==4.0.2)
Requires-Dist: attrs (==23.1.0)
Requires-Dist: backcall (==0.2.0)
Requires-Dist: backoff (==2.2.1)
Requires-Dist: certifi (==2023.7.22)
Requires-Dist: charset-normalizer (==3.2.0)
Requires-Dist: chroma-hnswlib (==0.7.1)
Requires-Dist: chromadb (==0.4.3)
Requires-Dist: click (==8.1.6)
Requires-Dist: cmake (==3.27.0)
Requires-Dist: colorama (==0.4.6)
Requires-Dist: coloredlogs (==15.0.1)
Requires-Dist: comm (==0.1.3)
Requires-Dist: contourpy (==1.1.0)
Requires-Dist: cycler (==0.11.0)
Requires-Dist: debugpy (==1.6.7)
Requires-Dist: decorator (==5.1.1)
Requires-Dist: exceptiongroup (==1.1.2)
Requires-Dist: executing (==1.2.0)
Requires-Dist: fastapi (==0.99.1)
Requires-Dist: filelock (==3.12.2)
Requires-Dist: fire (==0.5.0)
Requires-Dist: flatbuffers (==23.5.26)
Requires-Dist: fonttools (==4.41.1)
Requires-Dist: frozenlist (==1.4.0)
Requires-Dist: fsspec (==2023.6.0)
Requires-Dist: h11 (==0.14.0)
Requires-Dist: httptools (==0.6.0)
Requires-Dist: huggingface-hub (==0.16.4)
Requires-Dist: humanfriendly (==10.0)
Requires-Dist: idna (==3.4)
Requires-Dist: importlib-metadata (==6.8.0)
Requires-Dist: importlib-resources (==6.0.0)
Requires-Dist: ipykernel (==6.24.0)
Requires-Dist: ipython (==8.14.0)
Requires-Dist: jedi (==0.18.2)
Requires-Dist: jupyter-client (==8.3.0)
Requires-Dist: jupyter-core (==5.3.1)
Requires-Dist: kiwisolver (==1.4.4)
Requires-Dist: lit (==16.0.6)
Requires-Dist: matplotlib-inline (==0.1.6)
Requires-Dist: matplotlib (==3.7.2)
Requires-Dist: monotonic (==1.6)
Requires-Dist: mpmath (==1.3.0)
Requires-Dist: multidict (==6.0.4)
Requires-Dist: nest-asyncio (==1.5.6)
Requires-Dist: networkx (==3.1)
Requires-Dist: numpy (==1.25.1)
Requires-Dist: nvidia-cublas-cu11 (==11.10.3.66)
Requires-Dist: nvidia-cuda-cupti-cu11 (==11.7.101)
Requires-Dist: nvidia-cuda-nvrtc-cu11 (==11.7.99)
Requires-Dist: nvidia-cuda-runtime-cu11 (==11.7.99)
Requires-Dist: nvidia-cudnn-cu11 (==8.5.0.96)
Requires-Dist: nvidia-cufft-cu11 (==10.9.0.58)
Requires-Dist: nvidia-curand-cu11 (==10.2.10.91)
Requires-Dist: nvidia-cusolver-cu11 (==11.4.0.1)
Requires-Dist: nvidia-cusparse-cu11 (==11.7.4.91)
Requires-Dist: nvidia-nccl-cu11 (==2.14.3)
Requires-Dist: nvidia-nvtx-cu11 (==11.7.91)
Requires-Dist: onnxruntime (==1.15.1)
Requires-Dist: openai (==0.27.8)
Requires-Dist: overrides (==7.3.1)
Requires-Dist: packaging (==23.1)
Requires-Dist: pandas (==2.0.3)
Requires-Dist: parso (==0.8.3)
Requires-Dist: pexpect (==4.8.0)
Requires-Dist: pickleshare (==0.7.5)
Requires-Dist: platformdirs (==3.9.1)
Requires-Dist: posthog (==3.0.1)
Requires-Dist: prompt-toolkit (==3.0.39)
Requires-Dist: protobuf (==4.23.4)
Requires-Dist: psutil (==5.9.5)
Requires-Dist: ptyprocess (==0.7.0)
Requires-Dist: pulsar-client (==3.2.0)
Requires-Dist: pure-eval (==0.2.2)
Requires-Dist: pydantic (==1.10.12)
Requires-Dist: pyparsing (==3.0.9)
Requires-Dist: python-dateutil (==2.8.2)
Requires-Dist: pytz (==2023.3)
Requires-Dist: pyzmq (==25.1.0)
Requires-Dist: regex (==2023.6.3)
Requires-Dist: requests (==2.31.0)
Requires-Dist: safetensors (==0.3.1)
Requires-Dist: six (==1.16.0)
Requires-Dist: sniffio (==1.3.0)
Requires-Dist: stack-data (==0.6.2)
Requires-Dist: starlette (==0.27.0)
Requires-Dist: sympy (==1.12)
Requires-Dist: termcolor (==2.3.0)
Requires-Dist: tokenizers (==0.13.3)
Requires-Dist: torch (==2.0.1)
Requires-Dist: tornado (==6.3.2)
Requires-Dist: tqdm (==4.65.0)
Requires-Dist: traitlets (==5.9.0)
Requires-Dist: transformers (==4.31.0)
Requires-Dist: triton (==2.0.0)
Requires-Dist: typing-extensions (==4.7.1)
Requires-Dist: tzdata (==2023.3)
Requires-Dist: urllib3 (==2.0.4)
Requires-Dist: uvicorn (==0.23.1)
Requires-Dist: uvloop (==0.17.0)
Requires-Dist: watchfiles (==0.19.0)
Requires-Dist: wcwidth (==0.2.6)
Requires-Dist: websockets (==11.0.3)
Requires-Dist: yarl (==1.9.2)
Requires-Dist: zipp (==3.16.2)
